qcshared/__init__.py
qcshared/config/__init__.py
qcshared/config/config_utils.py
qcshared/config/constants.py
qcshared/config/defaults.py
qcshared/config/dmrg_config.py
qcshared/config/emulator_config.py
qcshared/config/emulator_input.py
qcshared/config/noise_config.py
qcshared/config/optimizer_config.py
qcshared/config/output_config.py
qcshared/config/resources.py
qcshared/config/statevector_config.py
qcshared/config/tebd_config.py
qcshared/config/trajectory_config.py
qcshared/io/__init__.py
qcshared/io/observables.py
qcshared/io/output.py
qcshared/json/__init__.py
qcshared/json/decode.py
qcshared/json/encode.py
qcshared/json/utils.py
qcshared/messaging/__init__.py
qcshared/messaging/message.py
qcshared/messaging/reporter.py
qcshared/noise_models/__init__.py
qcshared/noise_models/channel.py
qcshared/noise_models/gate.py
qcshared/noise_models/model.py
qcshared/noise_models/qubit.py
qcshared/noise_models/typing.py
qcshared/noise_models/utils.py
qcshared/observables/__init__.py
qcshared/observables/observables.py
qcshared/py.typed
qcshared/pydantic/__init__.py
qcshared/pydantic/models.py
qcshared/serializers/__init__.py
qcshared/serializers/circuit.py
qcshared/serializers/cirq_serializer.py
qcshared/serializers/custom_types.py
qcshared/serializers/qiskit_serializer.py
qcshared/serializers/serializer.py
qcshared/serializers/utils.py
qcshared/utils/__init__.py
qcshared/utils/circuit_generation_utils.py
qcshared/utils/constants.py
qcshared/utils/gate_maps.py
qcshared/utils/noise_model_utils.py
qcshared/utils/observable_utils.py
fermioniq_qc-1.5.2.dist-info/METADATA
fermioniq_qc-1.5.2.dist-info/WHEEL
fermioniq_qc-1.5.2.dist-info/RECORD
