Metadata-Version: 2.1
Name: fermioniq-qc
Version: 1.5.2
Summary: Utilities for quantum circuit emulation
Author: Fermioniq
Author-email: support@fermioniq.com
Requires-Python: >=3.10,<4.0
Classifier: Programming Language :: Python :: 3
Classifier: Programming Language :: Python :: 3.10
Classifier: Programming Language :: Python :: 3.11
Classifier: Programming Language :: Python :: 3.12
Requires-Dist: packaging (>=24.1,<25.0)
Requires-Dist: pydantic (>=2.8.2,<3.0.0)
Requires-Dist: rich (>=13.5.2,<14.0.0)
